morchaos/__init__.py
morchaos/cli/__init__.py
morchaos/cli/chatbot.py
morchaos/cli/duplicate.py
morchaos/cli/ebook_catalog.py
morchaos/cli/image_diff.py
morchaos/cli/source_diff.py
morchaos/cli/system_info.py
morchaos/core/__init__.py
morchaos/core/chatbot.py
morchaos/core/duplicate.py
morchaos/core/ebook.py
morchaos/core/file_utils.py
morchaos/core/image.py
morchaos/core/source.py
morchaos/core/system.py
morchaos/logger/__init__.py
morchaos-0.1.0.dist-info/entry_points.txt
morchaos-0.1.0.dist-info/METADATA
morchaos-0.1.0.dist-info/WHEEL
morchaos-0.1.0.dist-info/RECORD
