Metadata-Version: 2.4
Name: morchaos
Version: 0.1.0
Summary: A collection of utilities for file management, deduplication, and system monitoring
Author: Jones Chung
Author-email: jones.developer.chung@gmail.com
Requires-Python: >=3.10,<4.0
Classifier: Programming Language :: Python :: 3
Classifier: Programming Language :: Python :: 3.10
Classifier: Programming Language :: Python :: 3.11
Classifier: Programming Language :: Python :: 3.12
Classifier: Programming Language :: Python :: 3.13
Classifier: Programming Language :: Python :: 3.14
Requires-Dist: Pillow (>=10.0.0,<11.0.0)
Requires-Dist: click (>=8.1.0,<9.0.0)
Requires-Dist: ebooklib (>=0.18,<0.19)
Requires-Dist: imagehash (>=4.3.0,<5.0.0)
Requires-Dist: pdfplumber (>=0.9.0,<0.10.0)
Requires-Dist: psutil (>=5.9.0,<6.0.0)
Requires-Dist: python-docx (>=0.8.11,<0.9.0)
Requires-Dist: requests (>=2.31.0,<3.0.0)
